<?xml version="1.0" ?><annotation>
	<segmented>0</segmented>
	<folder>less_selected</folder>
	<size>
		<width>1280</width>
		<height>720</height>
	</size>
	<object>
		<bndbox>
			<xmin>546</xmin>
			<ymin>178</ymin>
			<ymax>708</ymax>
			<xmax>928</xmax>
		</bndbox>
		<difficult>0</difficult>
		<pose>Unspecified</pose>
		<name>Diver</name>
		<truncated>0</truncated>
	</object>
	<object>
		<bndbox>
			<xmin>642</xmin>
			<ymin>206</ymin>
			<ymax>328</ymax>
			<xmax>824</xmax>
		</bndbox>
		<difficult>0</difficult>
		<pose>Unspecified</pose>
		<name>Head</name>
		<truncated>0</truncated>
	</object>
	<object>
		<bndbox>
			<xmin>604</xmin>
			<ymin>304</ymin>
			<ymax>396</ymax>
			<xmax>708</xmax>
		</bndbox>
		<difficult>0</difficult>
		<pose>Unspecified</pose>
		<name>Hand</name>
		<truncated>0</truncated>
	</object>
	<filename>barbados_004_left_frame10258.jpg</filename>
</annotation>