<?xml version="1.0" ?><annotation>
	<segmented>0</segmented>
	<folder>less_selected</folder>
	<size>
		<width>640</width>
		<height>360</height>
	</size>
	<object>
		<bndbox>
			<xmin>233</xmin>
			<ymin>112</ymin>
			<ymax>252</ymax>
			<xmax>459</xmax>
		</bndbox>
		<difficult>0</difficult>
		<pose>Unspecified</pose>
		<name>Diver</name>
		<truncated>0</truncated>
	</object>
	
	
	
	<object>
		<bndbox>
			<xmin>418</xmin>
			<ymin>215</ymin>
			<ymax>244</ymax>
			<xmax>450</xmax>
		</bndbox>
		<difficult>0</difficult>
		<pose>Unspecified</pose>
		<name>Hand</name>
		<truncated>0</truncated>
	</object>
	<filename>following_image_1_642.jpg</filename>
</annotation>