<?xml version="1.0" ?><annotation>
	<segmented>0</segmented>
	<folder>less_selected</folder>
	<size>
		<width>640</width>
		<height>360</height>
	</size>
	
	<object>
		<bndbox>
			<xmin>339</xmin>
			<ymin>15</ymin>
			<ymax>143</ymax>
			<xmax>449</xmax>
		</bndbox>
		<difficult>0</difficult>
		<pose>Unspecified</pose>
		<name>Head</name>
		<truncated>0</truncated>
	</object>
	<object>
		<bndbox>
			<xmin>190</xmin>
			<ymin>69</ymin>
			<ymax>269</ymax>
			<xmax>327</xmax>
		</bndbox>
		<difficult>0</difficult>
		<pose>Unspecified</pose>
		<name>Hand</name>
		<truncated>0</truncated>
	</object>
	<filename>kingston-jim-up-frame0922.jpg</filename>
</annotation>