<?xml version="1.0" ?><annotation>
	<segmented>0</segmented>
	<folder>less_selected</folder>
	<size>
		<width>1280</width>
		<height>720</height>
	</size>
	<object>
		<bndbox>
			<xmin>388</xmin>
			<ymin>92</ymin>
			<ymax>588</ymax>
			<xmax>868</xmax>
		</bndbox>
		<difficult>0</difficult>
		<pose>Unspecified</pose>
		<name>Diver</name>
		<truncated>0</truncated>
	</object>
	<object>
		<bndbox>
			<xmin>666</xmin>
			<ymin>324</ymin>
			<ymax>534</ymax>
			<xmax>826</xmax>
		</bndbox>
		<difficult>0</difficult>
		<pose>Unspecified</pose>
		<name>Hand</name>
		<truncated>0</truncated>
	</object>
	<object>
		<bndbox>
			<xmin>442</xmin>
			<ymin>436</ymin>
			<ymax>556</ymax>
			<xmax>598</xmax>
		</bndbox>
		<difficult>0</difficult>
		<pose>Unspecified</pose>
		<name>Hand</name>
		<truncated>0</truncated>
	</object>
	<filename>seneca_004_left_frame01636.jpg</filename>
</annotation>