<?xml version="1.0" ?><annotation>
	<segmented>0</segmented>
	<folder>less_selected</folder>
	<size>
		<width>1280</width>
		<height>720</height>
	</size>
	<object>
		<bndbox>
			<xmin>498</xmin>
			<ymin>298</ymin>
			<ymax>716</ymax>
			<xmax>794</xmax>
		</bndbox>
		<difficult>0</difficult>
		<pose>Unspecified</pose>
		<name>Diver</name>
		<truncated>0</truncated>
	</object>
	<object>
		<bndbox>
			<xmin>640</xmin>
			<ymin>300</ymin>
			<ymax>412</ymax>
			<xmax>728</xmax>
		</bndbox>
		<difficult>0</difficult>
		<pose>Unspecified</pose>
		<name>Head</name>
		<truncated>0</truncated>
	</object>
	<object>
		<bndbox>
			<xmin>532</xmin>
			<ymin>506</ymin>
			<ymax>572</ymax>
			<xmax>604</xmax>
		</bndbox>
		<difficult>0</difficult>
		<pose>Unspecified</pose>
		<name>Hand</name>
		<truncated>0</truncated>
	</object>
	<object>
		<bndbox>
			<xmin>668</xmin>
			<ymin>510</ymin>
			<ymax>588</ymax>
			<xmax>750</xmax>
		</bndbox>
		<difficult>0</difficult>
		<pose>Unspecified</pose>
		<name>Hand</name>
		<truncated>0</truncated>
	</object>
	<filename>barbados_005_right_frame09206.jpg</filename>
</annotation>