<?xml version="1.0" ?><annotation>
	<segmented>0</segmented>
	<folder>less_selected</folder>
	<size>
		<width>640</width>
		<height>360</height>
	</size>
	<object>
		<bndbox>
			<xmin>31</xmin>
			<ymin>128</ymin>
			<ymax>320</ymax>
			<xmax>402</xmax>
		</bndbox>
		<difficult>0</difficult>
		<pose>Unspecified</pose>
		<name>Diver</name>
		<truncated>0</truncated>
	</object>
	
	<object>
		<bndbox>
			<xmin>31</xmin>
			<ymin>207</ymin>
			<ymax>259</ymax>
			<xmax>106</xmax>
		</bndbox>
		<difficult>0</difficult>
		<pose>Unspecified</pose>
		<name>Head</name>
		<truncated>0</truncated>
	</object>
	
	<object>
		<bndbox>
			<xmin>180</xmin>
			<ymin>280</ymin>
			<ymax>312</ymax>
			<xmax>226</xmax>
		</bndbox>
		<difficult>0</difficult>
		<pose>Unspecified</pose>
		<name>Hand</name>
		<truncated>0</truncated>
	</object>
	<filename>following_image_0_46022.jpg</filename>
</annotation>