<?xml version="1.0" ?><annotation>
	<segmented>0</segmented>
	<folder>less_selected</folder>
	<size>
		<width>640</width>
		<height>360</height>
	</size>
	<object>
		<bndbox>
			<xmin>198</xmin>
			<ymin>56</ymin>
			<ymax>338</ymax>
			<xmax>465</xmax>
		</bndbox>
		<difficult>0</difficult>
		<pose>Unspecified</pose>
		<name>Diver</name>
		<truncated>0</truncated>
	</object>
	
	<object>
		<bndbox>
			<xmin>277</xmin>
			<ymin>55</ymin>
			<ymax>153</ymax>
			<xmax>351</xmax>
		</bndbox>
		<difficult>0</difficult>
		<pose>Unspecified</pose>
		<name>Head</name>
		<truncated>0</truncated>
	</object>
	
	<object>
		<bndbox>
			<xmin>243</xmin>
			<ymin>127</ymin>
			<ymax>188</ymax>
			<xmax>309</xmax>
		</bndbox>
		<difficult>0</difficult>
		<pose>Unspecified</pose>
		<name>Hand</name>
		<truncated>0</truncated>
	</object>
	<filename>signs_image_1_125771.jpg</filename>
</annotation>