<?xml version="1.0" ?><annotation>
	<segmented>0</segmented>
	<folder>less_selected</folder>
	<size>
		<width>640</width>
		<height>360</height>
	</size>
	<object>
		<bndbox>
			<xmin>281</xmin>
			<ymin>155</ymin>
			<ymax>359</ymax>
			<xmax>498</xmax>
		</bndbox>
		<difficult>0</difficult>
		<pose>Unspecified</pose>
		<name>Diver</name>
		<truncated>0</truncated>
	</object>
	
	<object>
		<bndbox>
			<xmin>324</xmin>
			<ymin>154</ymin>
			<ymax>245</ymax>
			<xmax>397</xmax>
		</bndbox>
		<difficult>0</difficult>
		<pose>Unspecified</pose>
		<name>Head</name>
		<truncated>0</truncated>
	</object>
	<object>
		<bndbox>
			<xmin>301</xmin>
			<ymin>188</ymin>
			<ymax>276</ymax>
			<xmax>370</xmax>
		</bndbox>
		<difficult>0</difficult>
		<pose>Unspecified</pose>
		<name>Hand</name>
		<truncated>0</truncated>
	</object>
	<object>
		<bndbox>
			<xmin>402</xmin>
			<ymin>264</ymin>
			<ymax>307</ymax>
			<xmax>452</xmax>
		</bndbox>
		<difficult>0</difficult>
		<pose>Unspecified</pose>
		<name>Hand</name>
		<truncated>0</truncated>
	</object>
	<filename>signs_image_0_71557.jpg</filename>
</annotation>