<?xml version="1.0" ?><annotation>
	<segmented>0</segmented>
	<folder>less_selected</folder>
	<size>
		<width>1280</width>
		<height>720</height>
	</size>
	<object>
		<bndbox>
			<xmin>10</xmin>
			<ymin>4</ymin>
			<ymax>700</ymax>
			<xmax>958</xmax>
		</bndbox>
		<difficult>0</difficult>
		<pose>Unspecified</pose>
		<name>Diver</name>
		<truncated>0</truncated>
	</object>
	
	<object>
		<bndbox>
			<xmin>12</xmin>
			<ymin>50</ymin>
			<ymax>316</ymax>
			<xmax>194</xmax>
		</bndbox>
		<difficult>0</difficult>
		<pose>Unspecified</pose>
		<name>Hand</name>
		<truncated>0</truncated>
	</object>
	
	<object>
		<bndbox>
			<xmin>806</xmin>
			<ymin>374</ymin>
			<ymax>542</ymax>
			<xmax>964</xmax>
		</bndbox>
		<difficult>0</difficult>
		<pose>Unspecified</pose>
		<name>Hand</name>
		<truncated>0</truncated>
	</object>
	
	<filename>seneca_001_right_frame00043.jpg</filename>
</annotation>