<?xml version="1.0" ?><annotation>
	<segmented>0</segmented>
	<folder>less_selected</folder>
	<size>
		<width>1280</width>
		<height>720</height>
	</size>
	<object>
		<bndbox>
			<xmin>342</xmin>
			<ymin>64</ymin>
			<ymax>628</ymax>
			<xmax>1032</xmax>
		</bndbox>
		<difficult>0</difficult>
		<pose>Unspecified</pose>
		<name>Diver</name>
		<truncated>0</truncated>
	</object>
	<object>
		<bndbox>
			<xmin>532</xmin>
			<ymin>100</ymin>
			<ymax>362</ymax>
			<xmax>732</xmax>
		</bndbox>
		<difficult>0</difficult>
		<pose>Unspecified</pose>
		<name>Head</name>
		<truncated>0</truncated>
	</object>
	<object>
		<bndbox>
			<xmin>378</xmin>
			<ymin>470</ymin>
			<ymax>622</ymax>
			<xmax>546</xmax>
		</bndbox>
		<difficult>0</difficult>
		<pose>Unspecified</pose>
		<name>Hand</name>
		<truncated>0</truncated>
	</object>
	<object>
		<bndbox>
			<xmin>758</xmin>
			<ymin>244</ymin>
			<ymax>412</ymax>
			<xmax>926</xmax>
		</bndbox>
		<difficult>0</difficult>
		<pose>Unspecified</pose>
		<name>Hand</name>
		<truncated>0</truncated>
	</object>
	<filename>seneca_050_left_frame01268.jpg</filename>
</annotation>